ramps_trio/__init__.py
ramps_trio/status_1.py
ramps_trio/_clique/__init__.py
ramps_trio/_clique/group/__init__.py
ramps_trio/_licenses/gpl-3.0-standalone.html
ramps_trio/_status/status.proc.py
ramps_trio/_status/vows/1/status_1.py
ramps_trio/clouds/yahoo/read_CSV.py
ramps_trio-0.0.1.dist-info/METADATA
ramps_trio-0.0.1.dist-info/WHEEL
ramps_trio-0.0.1.dist-info/top_level.txt
ramps_trio-0.0.1.dist-info/RECORD
