Metadata-Version: 2.1
Name: ramps_trio
Version: 0.0.1
License: 
Requires-Dist: bracelet
Requires-Dist: click
Requires-Dist: pandas
